{"name":"qcheck_pandoc","version":"1.0.0","gleam-version-constraint":null,"modules":{"qcheck_pandoc":{"documentation":[],"type-aliases":{},"types":{},"constants":{},"functions":{"attributes_generator":{"documentation":null,"deprecation":null,"implementations":{"gleam":false,"uses-erlang-externals":true,"uses-javascript-externals":true,"can-run-on-erlang":true,"can-run-on-javascript":true},"parameters":[],"return":{"kind":"named","name":"Generator","package":"qcheck","module":"qcheck","parameters":[{"kind":"named","name":"Attributes","package":"pandi","module":"pandi","parameters":[]}]}},"block_generator":{"documentation":null,"deprecation":null,"implementations":{"gleam":false,"uses-erlang-externals":true,"uses-javascript-externals":true,"can-run-on-erlang":true,"can-run-on-javascript":true},"parameters":[],"return":{"kind":"named","name":"Generator","package":"qcheck","module":"qcheck","parameters":[{"kind":"named","name":"Block","package":"pandi","module":"pandi","parameters":[]}]}},"document_generator":{"documentation":null,"deprecation":null,"implementations":{"gleam":false,"uses-erlang-externals":true,"uses-javascript-externals":true,"can-run-on-erlang":true,"can-run-on-javascript":true},"parameters":[],"return":{"kind":"named","name":"Generator","package":"qcheck","module":"qcheck","parameters":[{"kind":"named","name":"Document","package":"pandi","module":"pandi","parameters":[]}]}},"inlines_generator":{"documentation":null,"deprecation":null,"implementations":{"gleam":false,"uses-erlang-externals":true,"uses-javascript-externals":true,"can-run-on-erlang":true,"can-run-on-javascript":true},"parameters":[],"return":{"kind":"named","name":"Generator","package":"qcheck","module":"qcheck","parameters":[{"kind":"named","name":"List","package":"","module":"gleam","parameters":[{"kind":"named","name":"Inline","package":"pandi","module":"pandi","parameters":[]}]}]}},"word_generator":{"documentation":null,"deprecation":null,"implementations":{"gleam":false,"uses-erlang-externals":true,"uses-javascript-externals":true,"can-run-on-erlang":true,"can-run-on-javascript":true},"parameters":[],"return":{"kind":"named","name":"Generator","package":"qcheck","module":"qcheck","parameters":[{"kind":"named","name":"String","package":"","module":"gleam","parameters":[]}]}}}}}}